setup.py
src/qc/__init__.py
src/qc/arbitrary.py
src/qc/basictypes.py
src/qc/state.py
src/qc/util.py
src/qc.egg-info/PKG-INFO
src/qc.egg-info/SOURCES.txt
src/qc.egg-info/dependency_links.txt
src/qc.egg-info/top_level.txt
src/qc.egg-info/zip-safe