Metadata-Version: 1.0
Name: qc
Version: 0.1
Summary: QuickCheck: randomized testing made trivial.
Home-page: https://github.com/Greplin/qc
Author: Peter Scott
Author-email: peter@greplin.com
License: Apache
Platform: UNKNOWN
